logfmt_logger/__init__.py
logfmt_logger-0.1.2.dist-info/LICENSE.rst
logfmt_logger-0.1.2.dist-info/WHEEL
logfmt_logger-0.1.2.dist-info/METADATA
logfmt_logger-0.1.2.dist-info/RECORD
