Metadata-Version: 2.1
Name: logfmt-logger
Version: 0.1.2
Summary: Logger following the logfmt format with sound defaults
Author: Michael Mercier
Author-email: michael.mercier@ryax.tech
Requires-Python: >=3.7,<4.0
Classifier: Programming Language :: Python :: 3
Classifier: Programming Language :: Python :: 3.7
Classifier: Programming Language :: Python :: 3.8
Classifier: Programming Language :: Python :: 3.9
